artefacts_toolkit_gazebo/__init__.py
artefacts_toolkit_gazebo/bridge.py
artefacts_toolkit_gazebo/gz.py
artefacts_toolkit_gazebo/version.py
artefacts_toolkit_gazebo-0.2.2.dist-info/METADATA
artefacts_toolkit_gazebo-0.2.2.dist-info/WHEEL
artefacts_toolkit_gazebo-0.2.2.dist-info/top_level.txt
artefacts_toolkit_gazebo-0.2.2.dist-info/RECORD
